netbox_rolesandgroups/__init__.py
netbox_rolesandgroups/api/__init__.py
netbox_rolesandgroups/api/serializers.py
netbox_rolesandgroups/api/urls.py
netbox_rolesandgroups/api/views.py
netbox_rolesandgroups/filtersets.py
netbox_rolesandgroups/forms.py
netbox_rolesandgroups/migrations/0001_initial.py
netbox_rolesandgroups/migrations/__init__.py
netbox_rolesandgroups/models.py
netbox_rolesandgroups/navigation.py
netbox_rolesandgroups/requirements.txt
netbox_rolesandgroups/search.py
netbox_rolesandgroups/tables.py
netbox_rolesandgroups/template_content.py
netbox_rolesandgroups/templates/netbox_rolesandgroups/role_edit.html
netbox_rolesandgroups/templates/netbox_rolesandgroups/subsystemrole_include.html
netbox_rolesandgroups/templates/netbox_rolesandgroups/systemrole.html
netbox_rolesandgroups/templates/netbox_rolesandgroups/systemrole_edit.html
netbox_rolesandgroups/templates/netbox_rolesandgroups/systemrole_include.html
netbox_rolesandgroups/templates/netbox_rolesandgroups/techrole.html
netbox_rolesandgroups/templates/netbox_rolesandgroups/techrole_edit.html
netbox_rolesandgroups/urls.py
netbox_rolesandgroups/views.py
netbox_rolesandgroups-0.2.3.dist-info/LICENSE
netbox_rolesandgroups-0.2.3.dist-info/METADATA
netbox_rolesandgroups-0.2.3.dist-info/WHEEL
netbox_rolesandgroups-0.2.3.dist-info/RECORD
